Workbook

Sheet Inputs
A1: House-Watch Pricing Model — Inputs
A2: Blue = change me. Black = calculated. Yellow = key assumption.
A4: COST PER VISIT (assumption)
A5: Crew time per visit (hours) | B5: 0.75 | C5: Visit + drive ≈ 30–45 min (Service Guide)
A6: Labor rate ($/crew-hour) | B6: 18 | C6: Brother wage (Service Guide)
A7: Vehicle / gas per visit ($) | B7: 5 | C7: Estimate
A8: Cost per visit | B8: =B5*B6+B7 -> 18.5
A10: VISITS PER MONTH BY CADENCE
A11: Monthly (1×/mo) | B11: 1
A12: Bi-weekly (every 2 wks) | B12: 2.17
A13: Weekly | B13: 4.33
A15: COMPETITOR ANCHOR (per single inspection)
A16: Anchor low (OBX First Watch) | B16: 65
A17: Anchor high (OBX First Watch) | B17: 85
A18: Anchor midpoint | B18: =AVERAGE(B16:B17) -> 75
A20: RATES — CURRENT vs PROPOSED ($/visit)
A21: Tier | B21: Current | C21: Proposed
A22: Monthly | B22: 50 | C22: 65
A23: Bi-weekly | B23: 45 | C23: 55
A24: Weekly | B24: 40 | C24: 50
A25: One-off / ad-hoc | B25: 75 | C25: 75
A26: Storm check | B26: 95 | C26: 95

Sheet Price Ladder
A1: Proposed Price Ladder vs Current vs Anchor
A3: Tier | B3: Visits/mo | C3: Current $/visit | D3: Proposed $/visit | E3: % change | F3: Anchor (single) | G3: Cost/visit | H3: Margin/visit (curr) | I3: Margin % curr | J3: Margin/visit (prop) | K3: Margin % prop
A4: Monthly | B4: =Inputs!B11 -> 1 | C4: =Inputs!B22 -> 50 | D4: =Inputs!C22 -> 65 | E4: =(D4-C4)/C4 -> 0.3 | F4: =Inputs!B18 -> 75 | G4: =Inputs!B8 -> 18.5 | H4: =C4-G4 -> 31.5 | I4: =H4/C4 -> 0.63 | J4: =D4-G4 -> 46.5 | K4: =J4/D4 -> 0.71538462
A5: Bi-weekly | B5: =Inputs!B12 -> 2.17 | C5: =Inputs!B23 -> 45 | D5: =Inputs!C23 -> 55 | E5: =(D5-C5)/C5 -> 0.22222222 | F5: =Inputs!B18 -> 75 | G5: =Inputs!B8 -> 18.5 | H5: =C5-G5 -> 26.5 | I5: =H5/C5 -> 0.58888889 | J5: =D5-G5 -> 36.5 | K5: =J5/D5 -> 0.66363636
A6: Weekly | B6: =Inputs!B13 -> 4.33 | C6: =Inputs!B24 -> 40 | D6: =Inputs!C24 -> 50 | E6: =(D6-C6)/C6 -> 0.25 | F6: =Inputs!B18 -> 75 | G6: =Inputs!B8 -> 18.5 | H6: =C6-G6 -> 21.5 | I6: =H6/C6 -> 0.5375 | J6: =D6-G6 -> 31.5 | K6: =J6/D6 -> 0.63
A7: One-off / ad-hoc | C7: =Inputs!B25 -> 75 | D7: =Inputs!C25 -> 75 | E7: =(D7-C7)/C7 -> 0 | F7: =Inputs!B18 -> 75 | G7: =Inputs!B8 -> 18.5 | H7: =C7-G7 -> 56.5 | I7: =H7/C7 -> 0.75333333 | J7: =D7-G7 -> 56.5 | K7: =J7/D7 -> 0.75333333
A8: Storm check | C8: =Inputs!B26 -> 95 | D8: =Inputs!C26 -> 95 | E8: =(D8-C8)/C8 -> 0 | F8: =Inputs!B18 -> 75 | G8: =Inputs!B8 -> 18.5 | H8: =C8-G8 -> 76.5 | I8: =H8/C8 -> 0.80526316 | J8: =D8-G8 -> 76.5 | K8: =J8/D8 -> 0.80526316
A10: Note: recurring tiers stay AT/BELOW the single-inspection anchor — the recurring discount is preserved even after the increase.

Sheet Revenue Impact
A1: Revenue Impact
A3: Per-client revenue (recurring tiers)
A4: Tier | B4: Visits/mo | C4: Current/mo | D4: Proposed/mo | E4: Δ/mo | F4: Current/yr | G4: Proposed/yr
A5: Monthly | B5: =Inputs!B11 -> 1 | C5: =Inputs!B22*Inputs!B11 -> 50 | D5: =Inputs!C22*Inputs!B11 -> 65 | E5: =D5-C5 -> 15 | F5: =C5*12 -> 600 | G5: =D5*12 -> 780
A6: Bi-weekly | B6: =Inputs!B12 -> 2.17 | C6: =Inputs!B23*Inputs!B12 -> 97.65 | D6: =Inputs!C23*Inputs!B12 -> 119.35 | E6: =D6-C6 -> 21.7 | F6: =C6*12 -> 1171.8 | G6: =D6*12 -> 1432.2
A7: Weekly | B7: =Inputs!B13 -> 4.33 | C7: =Inputs!B24*Inputs!B13 -> 173.2 | D7: =Inputs!C24*Inputs!B13 -> 216.5 | E7: =D7-C7 -> 43.3 | F7: =C7*12 -> 2078.4 | G7: =D7*12 -> 2598
A10: Blended portfolio mix (change me)
A11: % Monthly | B11: 0.5
A12: % Bi-weekly | B12: 0.3
A13: % Weekly | B13: 0.2
A14: Mix check (=100%) | B14: =SUM(B11:B13) -> 1
A16: Avg revenue / client / mo — current | B16: =B11*C5+B12*C6+B13*C7 -> 88.935
A17: Avg revenue / client / mo — proposed | B17: =B11*D5+B12*D6+B13*D7 -> 111.605
A19: Portfolio revenue at client counts (blended)
A20: Clients | B20: Current MRR | C20: Proposed MRR | D20: Δ MRR | E20: Δ Annual
A21: 5 | B21: =A21*$B$16 -> 444.675 | C21: =A21*$B$17 -> 558.025 | D21: =C21-B21 -> 113.35 | E21: =D21*12 -> 1360.2
A22: 10 | B22: =A22*$B$16 -> 889.35 | C22: =A22*$B$17 -> 1116.05 | D22: =C22-B22 -> 226.7 | E22: =D22*12 -> 2720.4
A23: 20 | B23: =A23*$B$16 -> 1778.7 | C23: =A23*$B$17 -> 2232.1 | D23: =C23-B23 -> 453.4 | E23: =D23*12 -> 5440.8
A24: 30 | B24: =A24*$B$16 -> 2668.05 | C24: =A24*$B$17 -> 3348.15 | D24: =C24-B24 -> 680.1 | E24: =D24*12 -> 8161.2
A26: MRR = monthly recurring revenue. Assumes the blended mix above; change mix or counts to test scenarios.

Sheet Positioning & Notes
A1: Positioning & Notes — DATA FOR RAY TO DECIDE (not a done decision)
A3: Why the anchor matters
A4: OBX First Watch is the only OBX home-watch competitor publishing prices: $65–$85 per single interior+exterior inspection,
A5: priced by drive distance, for 4–8 BR homes. Home Check OBX and Cottage Comforts keep pricing private.
A6: Our current recurring rates ($40–$50/visit) sit BELOW that single-inspection anchor.
A8: Proposed ladder logic
A9: Set recurring per-visit rates at/just under the anchor, with higher cadence = lower per-visit (volume reward):
A10: • Monthly $50 → $65 • Bi-weekly $45 → $55 • Weekly $40 → $50 • One-off $75 (keep) • Storm $95 (keep)
A11: Even at the proposed rates, recurring stays a discount to the $75 one-off and at/below the $65–85 single-inspection market.
A13: How to position the increase (suggested, not decided)
A14: 1. New clients first: quote all NEW house-watch clients at the proposed ladder immediately. Low risk, no churn.
A15: 2. Grandfather existing clients: keep their current rate for now, or step them up at a natural renewal/season start
... A26: OBX First Watch fees: https://www.obxfirstwatch.com/fees-feb-2021 | Internal: Service Guide, quote-pricing-benchmarks
